[
  {
    "file": "game:itemtypes/wearable/seraph/armor.json",
    "path": "/behaviors/0/propertiesByType/armor-head-scale-*bronze",
    "op": "replace",
    "value": {
      "Layers": [
        "Outer",
        "Middle"
      ],
      "Zones": [
        "Head",
        "Neck",
        "Face"
      ],
      "Resists": {
        "PiercingAttack": 4,
        "SlashingAttack": 4,
        "BluntAttack": 0
      },
      "FlatReduction": {
        "PiercingAttack": 1,
        "SlashingAttack": 1,
        "BluntAttack": 1
      },
      "PlayerStats": {
        "walkspeed": 0,
        "manipulationSpeed": -0.05,
        "steadyAim": -0.06,
        "healingeffectivness": -0.06,
        "hungerrate": 0.09
      }
    },
    "dependsOn": [
      {
        "modid": "armory"
      },
      {
        "modid": "anmitechco"
      },
      {
        "modid": "combatoverhaul"
      }
    ]
  },
  {
    "file": "game:itemtypes/wearable/seraph/armor.json",
    "path": "/behaviors/0/propertiesByType/armor-body-scale-*bronze",
    "op": "replace",
    "value": {
      "Layers": [
        "Outer",
        "Middle"
      ],
      "Zones": [
        "Torso",
        "Arms",
        "Hands"
      ],
      "Resists": {
        "PiercingAttack": 4,
        "SlashingAttack": 4,
        "BluntAttack": 0
      },
      "FlatReduction": {
        "PiercingAttack": 1,
        "SlashingAttack": 1,
        "BluntAttack": 1
      },
      "PlayerStats": {
        "walkspeed": -0.05,
        "manipulationSpeed": -0.1,
        "steadyAim": -0.17,
        "healingeffectivness": -0.06,
        "hungerrate": 0.09,
        "jumpHeightMul": -0.1
      }
    },
    "dependsOn": [
      {
        "modid": "armory"
      },
      {
        "modid": "anmitechco"
      },
      {
        "modid": "combatoverhaul"
      }
    ]
  },
  {
    "file": "game:itemtypes/wearable/seraph/armor.json",
    "path": "/behaviors/0/propertiesByType/armor-legs-scale-*bronze",
    "op": "replace",
    "value": {
      "Layers": [
        "Outer",
        "Middle"
      ],
      "Zones": [
        "Legs",
        "Feet"
      ],
      "Resists": {
        "PiercingAttack": 4,
        "SlashingAttack": 4,
        "BluntAttack": 0
      },
      "FlatReduction": {
        "PiercingAttack": 1,
        "SlashingAttack": 1,
        "BluntAttack": 1
      },
      "PlayerStats": {
        "walkspeed": -0.03,
        "manipulationSpeed": 0,
        "steadyAim": 0,
        "healingeffectivness": -0.06,
        "hungerrate": 0.06,
        "jumpHeightMul": -0.1
      }
    },
    "dependsOn": [
      {
        "modid": "armory"
      },
      {
        "modid": "anmitechco"
      },
      {
        "modid": "combatoverhaul"
      }
    ]
  }
]
